{
  "path_card": {
    "START": {
      "number": 0,
      "connections": { "UP": 1, "RIGHT": 1, "DOWN": 1, "LEFT": 1 }
    },
    "GOAL": {
      "number": 0,
      "connections": { "UP": 1, "RIGHT": 1, "DOWN": 1, "LEFT": 1 }
    },
    "END": {
      "number": 0,
      "connections": { "UP": 1, "RIGHT": 1, "DOWN": 1, "LEFT": 1 }
    },
    "ST-UR": {
      "number": 0,
      "connections": { "UP": 1, "RIGHT": 1, "DOWN": 0, "LEFT": 0 }
    },
    "ST-UL": {
      "number": 0,
      "connections": { "UP": 1, "RIGHT": 0, "DOWN": 0, "LEFT": 1 }
    },
    "URDL+": {
      "number": 5,
      "connections": { "UP": 1, "RIGHT": 1, "DOWN": 1, "LEFT": 1 }
    },
    "URD+": {
      "number": 5,
      "connections": { "UP": 1, "RIGHT": 1, "DOWN": 1, "LEFT": 0 }
    },
    "URL+": {
      "number": 5,
      "connections": { "UP": 1, "RIGHT": 1, "DOWN": 0, "LEFT": 1 }
    },
    "UR+": {
      "number": 5,
      "connections": { "UP": 1, "RIGHT": 1, "DOWN": 0, "LEFT": 0 }
    },
    "UL+": {
      "number": 4,
      "connections": { "UP": 1, "RIGHT": 0, "DOWN": 0, "LEFT": 1 }
    },
    "UD+": {
      "number": 4,
      "connections": { "UP": 1, "RIGHT": 0, "DOWN": 1, "LEFT": 0 }
    },
    "RL+": {
      "number": 3,
      "connections": { "UP": 0, "RIGHT": 1, "DOWN": 0, "LEFT": 1 }
    },
    "URDLx": {
      "number": 1,
      "connections": { "UP": -1, "RIGHT": -1, "DOWN": -1, "LEFT": -1 }
    },
    "URDx": {
      "number": 1,
      "connections": { "UP": -1, "RIGHT": -1, "DOWN": -1, "LEFT": 0 }
    },
    "URLx": {
      "number": 1,
      "connections": { "UP": -1, "RIGHT": -1, "DOWN": 0, "LEFT": -1 }
    },
    "URx": {
      "number": 1,
      "connections": { "UP": -1, "RIGHT": -1, "DOWN": 0, "LEFT": 0 }
    },
    "ULx": {
      "number": 1,
      "connections": { "UP": -1, "RIGHT": 0, "DOWN": 0, "LEFT": -1 }
    },
    "UDx": {
      "number": 1,
      "connections": { "UP": -1, "RIGHT": 0, "DOWN": -1, "LEFT": 0 }
    },
    "RLx": {
      "number": 1,
      "connections": { "UP": 0, "RIGHT": -1, "DOWN": 0, "LEFT": -1 }
    },
    "Ux": {
      "number": 1,
      "connections": { "UP": -1, "RIGHT": 0, "DOWN": 0, "LEFT": 0 }
    },
    "Rx": {
      "number": 1,
      "connections": { "UP": 0, "RIGHT": -1, "DOWN": 0, "LEFT": 0 }
    },
    "UR+DL+": {
      "number": 1,
      "connections": { "UP": 1, "RIGHT": 1, "DOWN": 2, "LEFT": 2 }
    },
    "UL+RD+": {
      "number": 1,
      "connections": { "UP": 1, "RIGHT": 2, "DOWN": 2, "LEFT": 1 }
    },
    "UD+RL+": {
      "number": 2,
      "connections": { "UP": 1, "RIGHT": 2, "DOWN": 1, "LEFT": 2 }
    },
    "UD+RLx": {
      "number": 1,
      "connections": { "UP": 1, "RIGHT": -1, "DOWN": 1, "LEFT": -1 }
    },
    "RL+UDx": {
      "number": 1,
      "connections": { "UP": -1, "RIGHT": 1, "DOWN": -1, "LEFT": 1 }
    },
    "UD+Rx": {
      "number": 1,
      "connections": { "UP": 1, "RIGHT": -1, "DOWN": 1, "LEFT": 0 }
    },
    "UL+Dx": {
      "number": 1,
      "connections": { "UP": 1, "RIGHT": 0, "DOWN": -1, "LEFT": 1 }
    },
    "RD+Ux": {
      "number": 1,
      "connections": { "UP": -1, "RIGHT": 1, "DOWN": 1, "LEFT": 0 }
    },
    "UR+Dx": {
      "number": 1,
      "connections": { "UP": 1, "RIGHT": 1, "DOWN": -1, "LEFT": 0 }
    },
    "UR+E": {
      "number": 1,
      "connections": { "UP": 1, "RIGHT": 1, "DOWN": 0, "LEFT": 0 }
    },
    "UL+E": {
      "number": 1,
      "connections": { "UP": 1, "RIGHT": 0, "DOWN": 0, "LEFT": 1 }
    },
    "UxE": {
      "number": 1,
      "connections": { "UP": 1, "RIGHT": 0, "DOWN": 0, "LEFT": 0 }
    },
    "RxE": {
      "number": 1,
      "connections": { "UP": 0, "RIGHT": 1, "DOWN": 0, "LEFT": 0 }
    },
    "UD+B": {
      "number": 1,
      "connections": { "UP": 1, "RIGHT": 0, "DOWN": 1, "LEFT": 0 }
    },
    "UR+B": {
      "number": 1,
      "connections": { "UP": 1, "RIGHT": 1, "DOWN": 0, "LEFT": 0 }
    },
    "RL+B": {
      "number": 1,
      "connections": { "UP": 0, "RIGHT": 1, "DOWN": 0, "LEFT": 1 }
    },
    "UL+V": {
      "number": 1,
      "connections": { "UP": 1, "RIGHT": 0, "DOWN": 0, "LEFT": 1 }
    },
    "RL+V": {
      "number": 1,
      "connections": { "UP": 0, "RIGHT": 1, "DOWN": 0, "LEFT": 1 }
    },
    "UD+RxV": {
      "number": 1,
      "connections": { "UP": 1, "RIGHT": -1, "DOWN": 1, "LEFT": 0 }
    },
    "URDL+C": {
      "number": 1,
      "connections": { "UP": 1, "RIGHT": 1, "DOWN": 1, "LEFT": 1 }
    },
    "URD+LxC": {
      "number": 1,
      "connections": { "UP": 1, "RIGHT": 1, "DOWN": 1, "LEFT": -1 }
    },
    "URL+DxC": {
      "number": 1,
      "connections": { "UP": 1, "RIGHT": 1, "DOWN": -1, "LEFT": 1 }
    },
    "RL+UxC": {
      "number": 1,
      "connections": { "UP": -1, "RIGHT": 1, "DOWN": 0, "LEFT": 1 }
    },
    "URD+C": {
      "number": 1,
      "connections": { "UP": 1, "RIGHT": 1, "DOWN": 1, "LEFT": 0 }
    },
    "URL+C": {
      "number": 3,
      "connections": { "UP": 1, "RIGHT": 1, "DOWN": 0, "LEFT": 1 }
    },
    "UxC": {
      "number": 1,
      "connections": { "UP": -1, "RIGHT": 0, "DOWN": 0, "LEFT": 0 }
    },
    "RxC": {
      "number": 1,
      "connections": { "UP": 0, "RIGHT": -1, "DOWN": 0, "LEFT": 0 }
    }
  },
  "action_card": {
    "Lamp": {
      "number": 2,
      "type": "Defensive"
    },
    "Pickaxe": {
      "number": 2,
      "type": "Defensive"
    },
    "Carriage": {
      "number": 2,
      "type": "Defensive"
    },
    "Lamp + Pickaxe": {
      "number": 1,
      "type": "Defensive"
    },
    "Lamp + Carriage": {
      "number": 1,
      "type": "Defensive"
    },
    "Pickaxe + Carriage": {
      "number": 1,
      "type": "Defensive"
    },
    "Broken Lamp": {
      "number": 3,
      "type": "Offensive"
    },
    "Broken Pickaxe": {
      "number": 3,
      "type": "Offensive"
    },
    "Broken Carriage": {
      "number": 3,
      "type": "Offensive"
    },
    "Rockfall": {
      "number": 4,
      "type": "Neutral"
    },
    "Map": {
      "number": 6,
      "type": "Neutral"
    },
    "Prison": {
      "number": 3,
      "type": "Offensive"
    },
    "Escape": {
      "number": 4,
      "type": "Defensive"
    },
    "Thief": {
      "number": 3,
      "type": "Offensive"
    },
    "Stop the Thief": {
      "number": 4,
      "type": "Defensive"
    },
    "Spy": {
      "number": 2,
      "type": "Neutral"
    },
    "Change Role": {
      "number": 1,
      "type": "Neutral"
    }
  },
  "roles": {
    "GreenDwarf": {
      "number": 4,
      "description": "Green Dwarf - You want to reach the gold at the end of the mine.",
      "team": "Green"
    },
    "BlueDwarf": {
      "number": 4,
      "description": "Blue Dwarf - You want to reach the gold at the end of the mine.",
      "team": "Blue"
    },
    "SabOOter": {
      "number": 3,
      "description": "SabOOter - You want to prevent the dwarfs from reaching the gold.",
      "team": "SabOOter"
    },
    "Geologist": {
      "number": 2,
      "description": "Geologist - You want to collect the most gems.",
      "team": "Geologist"
    },
    "Profiteur": {
      "number": 1,
      "description": "Profiteur - You always win, but less points, try to prevent others from winning.",
      "team": "Profiteur"
    },
    "Boss": {
      "number": 1,
      "description": "Boss - You want to reach the gold at the end of the mine.",
      "team": "GreenBlue"
    }
  }
}
